[
  {
    "id": 1,
    "projectId": "gas-price-finder",
    "title": "Buscador de direcciones y que Google te de el código postal",
    "dueDate": null
  },
  {
    "id": 2,
    "projectId": "speedy-basket",
    "title": "Init monorepo + Expo app",
    "status": "Completada",
    "createdAt": "01/01/2026",
    "note": "Crear repo (monorepo). App Expo + TypeScript. Estructura /app, /backend, /shared. Script pnpm dev:app. Done: app arranca en Expo Go y navegacion basica.",
    "order": 1,
    "completedAt": "01/01/2026"
  },
  {
    "id": 3,
    "projectId": "speedy-basket",
    "title": "SQLite schema + init",
    "status": "Completada",
    "createdAt": "01/01/2026",
    "note": "Crear helper SQLite. Tablas: stores, zones, products, product_locations, outbox_events. Done: crea BD en frio y permite insertar/leer registros.",
    "order": 2,
    "completedAt": "01/01/2026"
  },
  {
    "id": 4,
    "projectId": "speedy-basket",
    "title": "Import pack JSON local",
    "status": "Completada",
    "createdAt": "01/01/2026",
    "note": "JSON mock de tienda + zonas + productos. Import al arranque si la BD esta vacia. Guardar pack_version. Done: reinstalar app vuelve a tener datos, sin backend.",
    "order": 3,
    "completedAt": "01/01/2026"
  },
  {
    "id": 5,
    "projectId": "speedy-basket",
    "title": "Screens: List / Search / Product",
    "status": "Completada",
    "createdAt": "01/01/2026",
    "note": "Lista de la compra, busqueda, detalle producto con zona sugerida y botones Encontrado/No esta. Done: funciona offline y genera eventos.",
    "order": 4,
    "completedAt": "01/01/2026"
  },
  {
    "id": 6,
    "projectId": "speedy-basket",
    "title": "Outbox events local",
    "status": "Completada",
    "createdAt": "01/01/2026",
    "note": "Guardar eventos en outbox_events. Tipos: FOUND / NOT_FOUND. Marcar enviados. Done: eventos visibles en SQLite y persistentes.",
    "order": 5,
    "completedAt": "01/01/2026"
  },
  {
    "id": 7,
    "projectId": "speedy-basket",
    "title": "Zone map (SVG) minimo",
    "status": "Completada",
    "createdAt": "01/01/2026",
    "note": "SVG simple con zonas clicables. Mostrar zona probable del producto. Done: sin pasillos exactos y no bloquea flujo.",
    "order": 6,
    "completedAt": "01/01/2026"
  },
  {
    "id": 8,
    "projectId": "speedy-basket",
    "title": "Developer mode screens",
    "status": "Completada",
    "createdAt": "01/01/2026",
    "note": "Activacion oculta (gesto). Pantallas: DB Viewer (read-only), Outbox viewer, Reset + reimport pack. Done: inspeccion en movil sin backend.",
    "order": 7,
    "completedAt": "01/01/2026"
  },
  {
    "id": 9,
    "projectId": "speedy-basket",
    "title": "Configurar cuenta de Render y desplegar la API",
    "dueDate": null
  },
  {
    "id": 10,
    "projectId": "speedy-basket",
    "title": "Pulir confianza: acumulativo, umbrales y escaneo",
    "dueDate": null
  },
  {
    "id": 11,
    "projectId": "speedy-basket",
    "title": "Conectar proyecto a Expo EAS",
    "status": "Completada",
    "createdAt": "04/01/2026",
    "note": "Proyecto enlazado con EAS y runbook documentado.",
    "order": 8,
    "completedAt": "04/01/2026"
  },
  {
    "id": 12,
    "projectId": "speedy-basket",
    "title": "Navegacion con tabs",
    "status": "Completada",
    "createdAt": "04/01/2026",
    "note": "Tabs para Lista, Mapa, Dev y Settings.",
    "order": 9,
    "completedAt": "04/01/2026"
  },
  {
    "id": 13,
    "projectId": "speedy-basket",
    "title": "Internacionalizacion (ES/EN)",
    "status": "Completada",
    "createdAt": "04/01/2026",
    "note": "Strings en ES/EN con selector en Settings.",
    "order": 10,
    "completedAt": "04/01/2026"
  },
  {
    "id": 14,
    "projectId": "speedy-basket",
    "title": "Unificar Lista y Busqueda",
    "status": "Completada",
    "createdAt": "04/01/2026",
    "note": "Pantalla unica de lista/busqueda.",
    "order": 11,
    "completedAt": "04/01/2026"
  },
  {
    "id": 15,
    "projectId": "speedy-basket",
    "title": "Crear tiendas (CRUD basico)",
    "dueDate": null
  },
  {
    "id": 16,
    "projectId": "speedy-basket",
    "title": "Ampliar detalles de tiendas (direccion, etc.)",
    "dueDate": null
  },
  {
    "id": 17,
    "projectId": "speedy-basket",
    "title": "Aplicar SUPABASE_JWKS_URL en Render",
    "dueDate": null
  },
  {
    "id": 18,
    "projectId": "speedy-basket",
    "title": "Endpoints mínimos para listas privadas compartidas",
    "dueDate": null
  },
  {
    "id": 19,
    "projectId": "speedy-basket",
    "title": "Revisar duración del token JWT (expiry)",
    "dueDate": null
  },
  {
    "id": 20,
    "projectId": "speedy-basket",
    "title": "Crear nuevo usuario \"Bego\" para pruebas",
    "dueDate": null
  },
  {
    "id": 21,
    "projectId": "speedy-basket",
    "title": "Crear roles: usuario y administrador tienda",
    "dueDate": null
  },
  {
    "id": 22,
    "projectId": "speedy-basket",
    "title": "Crear rol \"adminitrador dios\" (solo para web/admin)",
    "dueDate": null
  },
  {
    "id": 23,
    "projectId": "speedy-basket",
    "title": "Añadir UI de compartir cestas (por ahora oculto)",
    "dueDate": null
  },
  {
    "id": 24,
    "projectId": "speedy-basket",
    "title": "Sincronizar borrado de cestas con Supabase",
    "dueDate": null
  },
  {
    "id": 25,
    "projectId": "loto-sync",
    "title": "Definir entidades y validaciones (boletos, numeros, grupos)",
    "dueDate": null
  },
  {
    "id": 29,
    "projectId": "loto-sync",
    "title": "UI movil: selector de sorteo/grupo",
    "dueDate": null
  },
  {
    "id": 30,
    "projectId": "loto-sync",
    "title": "UI movil: alta de boleto con subida de resguardo",
    "dueDate": null
  },
  {
    "id": 31,
    "projectId": "loto-sync",
    "title": "Revisar vulnerabilidades npm (3 high) en loto-sync",
    "dueDate": null
  }
]
